setup.cfg
setup.py
accio/__init__.py
accio/cli.py
accio/common.py
accio/network.py
accio/parser.py
accio/utils.py
accio.egg-info/PKG-INFO
accio.egg-info/SOURCES.txt
accio.egg-info/dependency_links.txt
accio.egg-info/entry_points.txt
accio.egg-info/requires.txt
accio.egg-info/top_level.txt
accio/commands/__init__.py
accio/commands/pull.py
accio/commands/send.py
accio/commands/translate.py
accio/commands/test/__init__.py
accio/commands/test/test_send.py
accio/commands/test/test_translate.py
accio/scm/__init__.py
accio/scm/diff.py
accio/scm/git.py
accio/scm/test/__init__.py
accio/scm/test/test_diff.py
accio/test/__init__.py
accio/test/test_linter.py