Metadata-Version: 1.0
Name: accio
Version: 0.1
Summary: Sends information from code editors to server
Home-page: https://github.com/isovector/take2
Author: Matt Maclean
Author-email: matthewcmaclean@gmail.com
License: UNKNOWN
Platform: UNKNOWN
